wapi/VERSION
wapi/__init__.py
wapi/auth.py
wapi/curves.py
wapi/events.py
wapi/session.py
wapi/util.py
wapi_python-0.7.15.dist-info/LICENSE
wapi_python-0.7.15.dist-info/METADATA
wapi_python-0.7.15.dist-info/WHEEL
wapi_python-0.7.15.dist-info/top_level.txt
wapi_python-0.7.15.dist-info/RECORD
