Metadata-Version: 2.1
Name: wapi-python
Version: 0.7.15
Summary: Volue Insight API python library
Home-page: https://www.volueinsight.com
Author: Volue Insight
Author-email: support.insight@volue.com
License-File: LICENSE
Requires-Dist: requests >=2.18
Requires-Dist: sseclient-py >=1.7
Requires-Dist: pytz
Requires-Dist: pandas >=0.21
Requires-Dist: future >=0.16
